dlio_profiler_py.cpython-39-x86_64-linux-gnu.so
dlio_profiler/__init__.py
dlio_profiler/logger.py
dlio_profiler/etc/modulefiles/brahma-1.0.0.lua
dlio_profiler/etc/modulefiles/cpp-logger-1.0.0.lua
dlio_profiler/etc/modulefiles/dlio_profiler-2.0.1.lua
dlio_profiler/include/brahma.h
dlio_profiler/include/brahma/brahma.h
dlio_profiler/include/brahma/brahma_config.hpp
dlio_profiler/include/brahma/enumeration.h
dlio_profiler/include/brahma/interceptor.h
dlio_profiler/include/brahma/logging.h
dlio_profiler/include/brahma/singleton.h
dlio_profiler/include/brahma/interface/interface.h
dlio_profiler/include/brahma/interface/interface_utility.h
dlio_profiler/include/brahma/interface/posix.h
dlio_profiler/include/brahma/interface/stdio.h
dlio_profiler/include/cpp-logger/clogger.h
dlio_profiler/include/cpp-logger/cpp_logger_config.hpp
dlio_profiler/include/cpp-logger/logger.h
dlio_profiler/include/dlio_profiler/dlio_profiler.h
dlio_profiler/include/dlio_profiler/dlio_profiler_config.hpp
dlio_profiler/include/dlio_profiler/core/constants.h
dlio_profiler/include/dlio_profiler/core/typedef.h
dlio_profiler/include/gotcha/gotcha.h
dlio_profiler/include/gotcha/gotcha_config.h
dlio_profiler/include/gotcha/gotcha_types.h
dlio_profiler/include/pybind11/attr.h
dlio_profiler/include/pybind11/buffer_info.h
dlio_profiler/include/pybind11/cast.h
dlio_profiler/include/pybind11/chrono.h
dlio_profiler/include/pybind11/common.h
dlio_profiler/include/pybind11/complex.h
dlio_profiler/include/pybind11/eigen.h
dlio_profiler/include/pybind11/embed.h
dlio_profiler/include/pybind11/eval.h
dlio_profiler/include/pybind11/functional.h
dlio_profiler/include/pybind11/gil.h
dlio_profiler/include/pybind11/gil_safe_call_once.h
dlio_profiler/include/pybind11/iostream.h
dlio_profiler/include/pybind11/numpy.h
dlio_profiler/include/pybind11/operators.h
dlio_profiler/include/pybind11/options.h
dlio_profiler/include/pybind11/pybind11.h
dlio_profiler_py-0.0.7.dist-info/LICENSE
dlio_profiler_py-0.0.7.dist-info/METADATA
dlio_profiler_py-0.0.7.dist-info/WHEEL
dlio_profiler_py-0.0.7.dist-info/top_level.txt
dlio_profiler_py-0.0.7.dist-info/RECORD
