Metadata-Version: 2.1
Name: dlio-profiler-py
Version: 0.0.7
Summary: I/O profiler for deep learning python apps. Specifically for dlio_benchmark.
Home-page: https://github.com/hariharan-devarajan/dlio-profiler
Author: Hariharan Devarajan (Hari)
License: UNKNOWN
Project-URL: Bug Reports, https://github.com/hariharan-devarajan/dlio-profiler/issues
Project-URL: Source, https://github.com/hariharan-devarajan/dlio-profiler
Keywords: profiler,deep learning,I/O,benchmark,NPZ,pytorch benchmark,tensorflow benchmark
Platform: UNKNOWN
Classifier: Development Status :: 3 - Alpha
Classifier: Intended Audience :: Science/Research
Classifier: Topic :: Software Development :: Build Tools
Classifier: License :: OSI Approved :: MIT License
Classifier: Programming Language :: Python :: 3.7
Classifier: Programming Language :: Python :: 3.8
Classifier: Programming Language :: Python :: 3.9
Classifier: Programming Language :: Python :: 3.10
Classifier: Programming Language :: Python :: 3 :: Only
Requires: pybind11
Requires: setuptools
Requires-Python: >=3.7
License-File: LICENSE
Requires-Dist: pybind11
Provides-Extra: dlp_analyzer
Requires-Dist: bokeh >=2.4.2 ; extra == 'dlp_analyzer'
Requires-Dist: pybind11 ; extra == 'dlp_analyzer'
Requires-Dist: zindex-py ==0.0.1 ; extra == 'dlp_analyzer'
Requires-Dist: pandas >=2.0.3 ; extra == 'dlp_analyzer'
Requires-Dist: dask >=2023.5.0 ; extra == 'dlp_analyzer'
Requires-Dist: distributed ; extra == 'dlp_analyzer'
Requires-Dist: numpy >=1.24.3 ; extra == 'dlp_analyzer'
Requires-Dist: pyarrow >=12.0.1 ; extra == 'dlp_analyzer'
Requires-Dist: rich >=13.6.0 ; extra == 'dlp_analyzer'
Requires-Dist: python-intervals >=1.10.0.post1 ; extra == 'dlp_analyzer'
Requires-Dist: matplotlib >=3.7.3 ; extra == 'dlp_analyzer'
Provides-Extra: test
Requires-Dist: pytest >=6.0 ; extra == 'test'
